ShenruqianchuEs6/README.md
ShenruqianchuEs6/__init__.py
ShenruqianchuEs6/__main__.py
ShenruqianchuEs6/file.epub
ShenruqianchuEs6/index.html
ShenruqianchuEs6/css/__init__.py
ShenruqianchuEs6/css/annotations.css
ShenruqianchuEs6/css/main.css
ShenruqianchuEs6/css/normalize.css
ShenruqianchuEs6/css/popup.css
ShenruqianchuEs6/font/__init__.py
ShenruqianchuEs6/font/fontello.eot
ShenruqianchuEs6/font/fontello.svg
ShenruqianchuEs6/font/fontello.ttf
ShenruqianchuEs6/font/fontello.woff
ShenruqianchuEs6/img/__init__.py
ShenruqianchuEs6/img/annotator-glyph-sprite.png
ShenruqianchuEs6/img/annotator-icon-sprite.png
ShenruqianchuEs6/img/apple-touch-icon.png
ShenruqianchuEs6/img/cancelfullscreen.png
ShenruqianchuEs6/img/close.png
ShenruqianchuEs6/img/fullscreen.png
ShenruqianchuEs6/img/loader.gif
ShenruqianchuEs6/img/menu-icon.png
ShenruqianchuEs6/img/save.png
ShenruqianchuEs6/img/saved.png
ShenruqianchuEs6/img/settings-s.png
ShenruqianchuEs6/img/settings.png
ShenruqianchuEs6/img/star.png
ShenruqianchuEs6/js/__init__.py
ShenruqianchuEs6/js/epub.js
ShenruqianchuEs6/js/epub.min.js
ShenruqianchuEs6/js/epub.min.map
ShenruqianchuEs6/js/hooks.min.js
ShenruqianchuEs6/js/hooks.min.map
ShenruqianchuEs6/js/reader.js
ShenruqianchuEs6/js/reader.js.map
ShenruqianchuEs6/js/reader.min.js
ShenruqianchuEs6/js/reader.min.map
ShenruqianchuEs6/js/hooks/__init__.py
ShenruqianchuEs6/js/hooks/extensions/__init__.py
ShenruqianchuEs6/js/hooks/extensions/highlight.js
ShenruqianchuEs6/js/libs/__init__.py
ShenruqianchuEs6/js/libs/jquery.min.js
ShenruqianchuEs6/js/libs/localforage.min.js
ShenruqianchuEs6/js/libs/screenfull.js
ShenruqianchuEs6/js/libs/screenfull.min.js
ShenruqianchuEs6/js/libs/zip.min.js
ShenruqianchuEs6/js/plugins/__init__.py
ShenruqianchuEs6/js/plugins/hypothesis.js
ShenruqianchuEs6/js/plugins/search.js
shenruqianchu_es6-2024.3.1.0.dist-info/METADATA
shenruqianchu_es6-2024.3.1.0.dist-info/WHEEL
shenruqianchu_es6-2024.3.1.0.dist-info/entry_points.txt
shenruqianchu_es6-2024.3.1.0.dist-info/top_level.txt
shenruqianchu_es6-2024.3.1.0.dist-info/RECORD
